EzyDB/__init__.py
EzyDB/main.py
EzyDB-0.1.0.dist-info/LICENSE
EzyDB-0.1.0.dist-info/METADATA
EzyDB-0.1.0.dist-info/WHEEL
EzyDB-0.1.0.dist-info/entry_points.txt
EzyDB-0.1.0.dist-info/top_level.txt
EzyDB-0.1.0.dist-info/RECORD
