Metadata-Version: 2.1
Name: EzyDB
Version: 0.1.0
Summary: EzyDB is a lightweight, file-based NoSQL database system designed for Python developers.
Author: Rakesh Kanna
Author-email: rakeshkanna0108@gmail.com
License: MIT
Keywords: database,db,nosql,json,bson,storage,store
License-File: LICENSE
